{
  "version": "3.0.0-alpha.1",
  "runId": "zeromemory-2026-03-21T10-24-02-rainy_after_class",
  "createdAt": "2026-03-21T10:25:53.377Z",
  "lane": "life_record",
  "freshness": {
    "weatherSignal": "小雨",
    "locationName": "Shanghai",
    "routineWindow": "after_class"
  },
  "narrative": {
    "premise": "把书包侧袋里揉成一团的纸巾拿出来时，发现它被雨水洇湿的边缘刚好晕开了一小片模糊的蓝色，像是钢笔漏墨，又像是天空掉下来的一角。",
    "microPlot": [
      "放学后，在空荡的走廊里整理书包侧袋。",
      "手指碰到一团湿软的旧纸巾，下意识想拿出来丢掉。",
      "展开时，发现被雨水洇湿的边缘晕染开一小片不规则的淡蓝色痕迹。",
      "动作停住了，盯着那团模糊的蓝色看了几秒。"
    ],
    "sensoryFocus": "像顺手留下的一段真实生活",
    "emotionalLanding": "那片偶然的、安静的蓝色，让原本要被丢弃的瞬间，有了一点可以被记住的质地。"
  },
  "visual": {
    "mode": "trace_led_life_record",
    "presenceMode": "partial_presence",
    "characterPresenceTarget": "clear_character_presence",
    "concreteSceneCues": [
      "捏着湿纸巾的指尖",
      "纸巾上晕开的淡蓝色水痕",
      "走廊窗边昏暗的天光映在侧脸上"
    ],
    "sceneNotes": [
      "context: school_transition_window",
      "weather: 小雨",
      "character_presence: the protagonist should be clearly readable in the frame through face, posture, or fuller-body action while the lived event stays primary"
    ],
    "characterTraceCues": [
      "hand_with_object",
      "sleeve_edge",
      "hair_tip_or_red_hairclip",
      "reflection_or_shadow_hint"
    ]
  },
  "sceneSemantics": {
    "runtimeMode": "living_character_zero_memory",
    "supportBoundIds": [
      "window_after_class",
      "weather_rain"
    ],
    "supportObjectRefs": [],
    "supportPlaceRef": "",
    "supportRoutineRef": "",
    "activeExternalEventIds": []
  }
}